{
  "generated_at": "2026-03-25T09:58:01.386414+00:00",
  "artifacts": [
    {
      "station": "greenwich",
      "type": "hourly_resampled",
      "source": "PEINP_GR_WeatherStn_Dec2025.csv",
      "path": "data/processed/greenwich/station_hourly.csv",
      "rows": 227,
      "timestamp": "2026-03-25T09:57:55.323055+00:00"
    },
    {
      "station": "greenwich",
      "type": "daily_resampled",
      "source": "PEINP_GR_WeatherStn_Dec2025.csv",
      "path": "data/processed/greenwich/station_daily.csv",
      "rows": 31,
      "timestamp": "2026-03-25T09:57:55.323068+00:00"
    },
    {
      "station": "greenwich",
      "type": "hourly_resampled",
      "source": "PEINP_GR_WeatherStn_Nov2025.csv",
      "path": "data/processed/greenwich/station_hourly.csv",
      "rows": 720,
      "timestamp": "2026-03-25T09:57:55.398016+00:00"
    },
    {
      "station": "greenwich",
      "type": "daily_resampled",
      "source": "PEINP_GR_WeatherStn_Nov2025.csv",
      "path": "data/processed/greenwich/station_daily.csv",
      "rows": 31,
      "timestamp": "2026-03-25T09:57:55.398023+00:00"
    },
    {
      "station": "greenwich",
      "type": "hourly_resampled",
      "source": "PEINP_GR_WeatherStn_Oct2025.csv",
      "path": "data/processed/greenwich/station_hourly.csv",
      "rows": 4,
      "timestamp": "2026-03-25T09:57:55.409248+00:00"
    },
    {
      "station": "greenwich",
      "type": "daily_resampled",
      "source": "PEINP_GR_WeatherStn_Oct2025.csv",
      "path": "data/processed/greenwich/station_daily.csv",
      "rows": 1,
      "timestamp": "2026-03-25T09:57:55.409254+00:00"
    },
    {
      "station": "greenwich",
      "type": "hourly_resampled",
      "source": "PEINP_GR_WeatherStn_Feb2026.csv",
      "path": "data/processed/greenwich/station_hourly.csv",
      "rows": 198,
      "timestamp": "2026-03-25T09:57:55.436645+00:00"
    },
    {
      "station": "greenwich",
      "type": "daily_resampled",
      "source": "PEINP_GR_WeatherStn_Feb2026.csv",
      "path": "data/processed/greenwich/station_daily.csv",
      "rows": 28,
      "timestamp": "2026-03-25T09:57:55.436651+00:00"
    },
    {
      "station": "greenwich",
      "type": "hourly_resampled",
      "source": "PEINP_GR_WeatherStn_Jan2026.csv",
      "path": "data/processed/greenwich/station_hourly.csv",
      "rows": 744,
      "timestamp": "2026-03-25T09:57:55.512162+00:00"
    },
    {
      "station": "greenwich",
      "type": "daily_resampled",
      "source": "PEINP_GR_WeatherStn_Jan2026.csv",
      "path": "data/processed/greenwich/station_daily.csv",
      "rows": 32,
      "timestamp": "2026-03-25T09:57:55.512169+00:00"
    },
    {
      "station": "greenwich",
      "type": "hourly_resampled",
      "source": "PEINP_GR_WeatherStn_Mar2026.csv",
      "path": "data/processed/greenwich/station_hourly.csv",
      "rows": 23,
      "timestamp": "2026-03-25T09:57:55.523016+00:00"
    },
    {
      "station": "greenwich",
      "type": "daily_resampled",
      "source": "PEINP_GR_WeatherStn_Mar2026.csv",
      "path": "data/processed/greenwich/station_daily.csv",
      "rows": 23,
      "timestamp": "2026-03-25T09:57:55.523022+00:00"
    },
    {
      "station": "greenwich",
      "type": "hourly_resampled",
      "source": "PEINP_GR_WeatherStn_Dec2022.csv",
      "path": "data/processed/greenwich/station_hourly.csv",
      "rows": 744,
      "timestamp": "2026-03-25T09:57:55.725262+00:00"
    },
    {
      "station": "greenwich",
      "type": "daily_resampled",
      "source": "PEINP_GR_WeatherStn_Dec2022.csv",
      "path": "data/processed/greenwich/station_daily.csv",
      "rows": 32,
      "timestamp": "2026-03-25T09:57:55.725268+00:00"
    },
    {
      "station": "greenwich",
      "type": "hourly_resampled",
      "source": "PEINP_GR_WeatherStn_Nov2022.csv",
      "path": "data/processed/greenwich/station_hourly.csv",
      "rows": 721,
      "timestamp": "2026-03-25T09:57:55.913425+00:00"
    },
    {
      "station": "greenwich",
      "type": "daily_resampled",
      "source": "PEINP_GR_WeatherStn_Nov2022.csv",
      "path": "data/processed/greenwich/station_daily.csv",
      "rows": 31,
      "timestamp": "2026-03-25T09:57:55.913432+00:00"
    },
    {
      "station": "greenwich",
      "type": "hourly_resampled",
      "source": "PEINP_GR_WeatherStn_Oct2022.csv",
      "path": "data/processed/greenwich/station_hourly.csv",
      "rows": 131,
      "timestamp": "2026-03-25T09:57:55.951453+00:00"
    },
    {
      "station": "greenwich",
      "type": "daily_resampled",
      "source": "PEINP_GR_WeatherStn_Oct2022.csv",
      "path": "data/processed/greenwich/station_daily.csv",
      "rows": 8,
      "timestamp": "2026-03-25T09:57:55.951460+00:00"
    },
    {
      "station": "greenwich",
      "type": "hourly_resampled",
      "source": "PEINP_GR_WeatherStn_Apr2023.csv",
      "path": "data/processed/greenwich/station_hourly.csv",
      "rows": 720,
      "timestamp": "2026-03-25T09:57:56.115381+00:00"
    },
    {
      "station": "greenwich",
      "type": "daily_resampled",
      "source": "PEINP_GR_WeatherStn_Apr2023.csv",
      "path": "data/processed/greenwich/station_daily.csv",
      "rows": 31,
      "timestamp": "2026-03-25T09:57:56.115387+00:00"
    },
    {
      "station": "greenwich",
      "type": "hourly_resampled",
      "source": "PEINP_GR_WeatherStn_Aug2023.csv",
      "path": "data/processed/greenwich/station_hourly.csv",
      "rows": 744,
      "timestamp": "2026-03-25T09:57:56.185740+00:00"
    },
    {
      "station": "greenwich",
      "type": "daily_resampled",
      "source": "PEINP_GR_WeatherStn_Aug2023.csv",
      "path": "data/processed/greenwich/station_daily.csv",
      "rows": 32,
      "timestamp": "2026-03-25T09:57:56.185746+00:00"
    },
    {
      "station": "greenwich",
      "type": "hourly_resampled",
      "source": "PEINP_GR_WeatherStn_Dec2023.csv",
      "path": "data/processed/greenwich/station_hourly.csv",
      "rows": 740,
      "timestamp": "2026-03-25T09:57:56.254329+00:00"
    },
    {
      "station": "greenwich",
      "type": "daily_resampled",
      "source": "PEINP_GR_WeatherStn_Dec2023.csv",
      "path": "data/processed/greenwich/station_daily.csv",
      "rows": 31,
      "timestamp": "2026-03-25T09:57:56.254335+00:00"
    },
    {
      "station": "greenwich",
      "type": "hourly_resampled",
      "source": "PEINP_GR_WeatherStn_Feb2023.csv",
      "path": "data/processed/greenwich/station_hourly.csv",
      "rows": 672,
      "timestamp": "2026-03-25T09:57:56.410500+00:00"
    },
    {
      "station": "greenwich",
      "type": "daily_resampled",
      "source": "PEINP_GR_WeatherStn_Feb2023.csv",
      "path": "data/processed/greenwich/station_daily.csv",
      "rows": 29,
      "timestamp": "2026-03-25T09:57:56.410507+00:00"
    },
    {
      "station": "greenwich",
      "type": "hourly_resampled",
      "source": "PEINP_GR_WeatherStn_Jan2023.csv",
      "path": "data/processed/greenwich/station_hourly.csv",
      "rows": 744,
      "timestamp": "2026-03-25T09:57:56.579942+00:00"
    },
    {
      "station": "greenwich",
      "type": "daily_resampled",
      "source": "PEINP_GR_WeatherStn_Jan2023.csv",
      "path": "data/processed/greenwich/station_daily.csv",
      "rows": 32,
      "timestamp": "2026-03-25T09:57:56.579949+00:00"
    },
    {
      "station": "greenwich",
      "type": "hourly_resampled",
      "source": "PEINP_GR_WeatherStn_Jul2023.csv",
      "path": "data/processed/greenwich/station_hourly.csv",
      "rows": 744,
      "timestamp": "2026-03-25T09:57:56.650733+00:00"
    },
    {
      "station": "greenwich",
      "type": "daily_resampled",
      "source": "PEINP_GR_WeatherStn_Jul2023.csv",
      "path": "data/processed/greenwich/station_daily.csv",
      "rows": 32,
      "timestamp": "2026-03-25T09:57:56.650740+00:00"
    },
    {
      "station": "greenwich",
      "type": "hourly_resampled",
      "source": "PEINP_GR_WeatherStn_Jun2023.csv",
      "path": "data/processed/greenwich/station_hourly.csv",
      "rows": 720,
      "timestamp": "2026-03-25T09:57:56.719959+00:00"
    },
    {
      "station": "greenwich",
      "type": "daily_resampled",
      "source": "PEINP_GR_WeatherStn_Jun2023.csv",
      "path": "data/processed/greenwich/station_daily.csv",
      "rows": 31,
      "timestamp": "2026-03-25T09:57:56.719965+00:00"
    },
    {
      "station": "greenwich",
      "type": "hourly_resampled",
      "source": "PEINP_GR_WeatherStn_Mar2023.csv",
      "path": "data/processed/greenwich/station_hourly.csv",
      "rows": 743,
      "timestamp": "2026-03-25T09:57:56.887916+00:00"
    },
    {
      "station": "greenwich",
      "type": "daily_resampled",
      "source": "PEINP_GR_WeatherStn_Mar2023.csv",
      "path": "data/processed/greenwich/station_daily.csv",
      "rows": 32,
      "timestamp": "2026-03-25T09:57:56.887922+00:00"
    },
    {
      "station": "greenwich",
      "type": "hourly_resampled",
      "source": "PEINP_GR_WeatherStn_May2023.csv",
      "path": "data/processed/greenwich/station_hourly.csv",
      "rows": 598,
      "timestamp": "2026-03-25T09:57:56.946451+00:00"
    },
    {
      "station": "greenwich",
      "type": "daily_resampled",
      "source": "PEINP_GR_WeatherStn_May2023.csv",
      "path": "data/processed/greenwich/station_daily.csv",
      "rows": 27,
      "timestamp": "2026-03-25T09:57:56.946458+00:00"
    },
    {
      "station": "greenwich",
      "type": "hourly_resampled",
      "source": "PEINP_GR_WeatherStn_Nov2023.csv",
      "path": "data/processed/greenwich/station_hourly.csv",
      "rows": 721,
      "timestamp": "2026-03-25T09:57:57.024270+00:00"
    },
    {
      "station": "greenwich",
      "type": "daily_resampled",
      "source": "PEINP_GR_WeatherStn_Nov2023.csv",
      "path": "data/processed/greenwich/station_daily.csv",
      "rows": 31,
      "timestamp": "2026-03-25T09:57:57.024278+00:00"
    },
    {
      "station": "greenwich",
      "type": "hourly_resampled",
      "source": "PEINP_GR_WeatherStn_Oct2023.csv",
      "path": "data/processed/greenwich/station_hourly.csv",
      "rows": 744,
      "timestamp": "2026-03-25T09:57:57.114758+00:00"
    },
    {
      "station": "greenwich",
      "type": "daily_resampled",
      "source": "PEINP_GR_WeatherStn_Oct2023.csv",
      "path": "data/processed/greenwich/station_daily.csv",
      "rows": 32,
      "timestamp": "2026-03-25T09:57:57.114764+00:00"
    },
    {
      "station": "greenwich",
      "type": "hourly_resampled",
      "source": "PEINP_GR_WeatherStn_Sep2023.csv",
      "path": "data/processed/greenwich/station_hourly.csv",
      "rows": 720,
      "timestamp": "2026-03-25T09:57:57.182307+00:00"
    },
    {
      "station": "greenwich",
      "type": "daily_resampled",
      "source": "PEINP_GR_WeatherStn_Sep2023.csv",
      "path": "data/processed/greenwich/station_daily.csv",
      "rows": 31,
      "timestamp": "2026-03-25T09:57:57.182314+00:00"
    },
    {
      "station": "greenwich",
      "type": "hourly_resampled",
      "source": "PEINP_GR_WeatherStn_Apr2024.csv",
      "path": "data/processed/greenwich/station_hourly.csv",
      "rows": 720,
      "timestamp": "2026-03-25T09:57:57.250795+00:00"
    },
    {
      "station": "greenwich",
      "type": "daily_resampled",
      "source": "PEINP_GR_WeatherStn_Apr2024.csv",
      "path": "data/processed/greenwich/station_daily.csv",
      "rows": 31,
      "timestamp": "2026-03-25T09:57:57.250802+00:00"
    },
    {
      "station": "greenwich",
      "type": "hourly_resampled",
      "source": "PEINP_GR_WeatherStn_Aug2024.csv",
      "path": "data/processed/greenwich/station_hourly.csv",
      "rows": 744,
      "timestamp": "2026-03-25T09:57:57.352905+00:00"
    },
    {
      "station": "greenwich",
      "type": "daily_resampled",
      "source": "PEINP_GR_WeatherStn_Aug2024.csv",
      "path": "data/processed/greenwich/station_daily.csv",
      "rows": 32,
      "timestamp": "2026-03-25T09:57:57.352911+00:00"
    },
    {
      "station": "greenwich",
      "type": "hourly_resampled",
      "source": "PEINP_GR_WeatherStn_Dec2024.csv",
      "path": "data/processed/greenwich/station_hourly.csv",
      "rows": 744,
      "timestamp": "2026-03-25T09:57:57.424957+00:00"
    },
    {
      "station": "greenwich",
      "type": "daily_resampled",
      "source": "PEINP_GR_WeatherStn_Dec2024.csv",
      "path": "data/processed/greenwich/station_daily.csv",
      "rows": 32,
      "timestamp": "2026-03-25T09:57:57.424964+00:00"
    },
    {
      "station": "greenwich",
      "type": "hourly_resampled",
      "source": "PEINP_GR_WeatherStn_Feb2024.csv",
      "path": "data/processed/greenwich/station_hourly.csv",
      "rows": 696,
      "timestamp": "2026-03-25T09:57:57.489010+00:00"
    },
    {
      "station": "greenwich",
      "type": "daily_resampled",
      "source": "PEINP_GR_WeatherStn_Feb2024.csv",
      "path": "data/processed/greenwich/station_daily.csv",
      "rows": 30,
      "timestamp": "2026-03-25T09:57:57.489017+00:00"
    },
    {
      "station": "greenwich",
      "type": "hourly_resampled",
      "source": "PEINP_GR_WeatherStn_Jan2024.csv",
      "path": "data/processed/greenwich/station_hourly.csv",
      "rows": 744,
      "timestamp": "2026-03-25T09:57:57.553598+00:00"
    },
    {
      "station": "greenwich",
      "type": "daily_resampled",
      "source": "PEINP_GR_WeatherStn_Jan2024.csv",
      "path": "data/processed/greenwich/station_daily.csv",
      "rows": 32,
      "timestamp": "2026-03-25T09:57:57.553604+00:00"
    },
    {
      "station": "greenwich",
      "type": "hourly_resampled",
      "source": "PEINP_GR_WeatherStn_Jul2024.csv",
      "path": "data/processed/greenwich/station_hourly.csv",
      "rows": 744,
      "timestamp": "2026-03-25T09:57:57.625789+00:00"
    },
    {
      "station": "greenwich",
      "type": "daily_resampled",
      "source": "PEINP_GR_WeatherStn_Jul2024.csv",
      "path": "data/processed/greenwich/station_daily.csv",
      "rows": 32,
      "timestamp": "2026-03-25T09:57:57.625796+00:00"
    },
    {
      "station": "greenwich",
      "type": "hourly_resampled",
      "source": "PEINP_GR_WeatherStn_Jun2024.csv",
      "path": "data/processed/greenwich/station_hourly.csv",
      "rows": 720,
      "timestamp": "2026-03-25T09:57:57.695603+00:00"
    },
    {
      "station": "greenwich",
      "type": "daily_resampled",
      "source": "PEINP_GR_WeatherStn_Jun2024.csv",
      "path": "data/processed/greenwich/station_daily.csv",
      "rows": 31,
      "timestamp": "2026-03-25T09:57:57.695610+00:00"
    },
    {
      "station": "greenwich",
      "type": "hourly_resampled",
      "source": "PEINP_GR_WeatherStn_Mar2024.csv",
      "path": "data/processed/greenwich/station_hourly.csv",
      "rows": 743,
      "timestamp": "2026-03-25T09:57:57.793552+00:00"
    },
    {
      "station": "greenwich",
      "type": "daily_resampled",
      "source": "PEINP_GR_WeatherStn_Mar2024.csv",
      "path": "data/processed/greenwich/station_daily.csv",
      "rows": 32,
      "timestamp": "2026-03-25T09:57:57.793559+00:00"
    },
    {
      "station": "greenwich",
      "type": "hourly_resampled",
      "source": "PEINP_GR_WeatherStn_May2024.csv",
      "path": "data/processed/greenwich/station_hourly.csv",
      "rows": 744,
      "timestamp": "2026-03-25T09:57:57.898559+00:00"
    },
    {
      "station": "greenwich",
      "type": "daily_resampled",
      "source": "PEINP_GR_WeatherStn_May2024.csv",
      "path": "data/processed/greenwich/station_daily.csv",
      "rows": 32,
      "timestamp": "2026-03-25T09:57:57.898566+00:00"
    },
    {
      "station": "greenwich",
      "type": "hourly_resampled",
      "source": "PEINP_GR_WeatherStn_Nov2024.csv",
      "path": "data/processed/greenwich/station_hourly.csv",
      "rows": 721,
      "timestamp": "2026-03-25T09:57:57.984493+00:00"
    },
    {
      "station": "greenwich",
      "type": "daily_resampled",
      "source": "PEINP_GR_WeatherStn_Nov2024.csv",
      "path": "data/processed/greenwich/station_daily.csv",
      "rows": 31,
      "timestamp": "2026-03-25T09:57:57.984499+00:00"
    },
    {
      "station": "greenwich",
      "type": "hourly_resampled",
      "source": "PEINP_GR_WeatherStn_Oct2024.csv",
      "path": "data/processed/greenwich/station_hourly.csv",
      "rows": 744,
      "timestamp": "2026-03-25T09:57:58.054838+00:00"
    },
    {
      "station": "greenwich",
      "type": "daily_resampled",
      "source": "PEINP_GR_WeatherStn_Oct2024.csv",
      "path": "data/processed/greenwich/station_daily.csv",
      "rows": 32,
      "timestamp": "2026-03-25T09:57:58.054844+00:00"
    },
    {
      "station": "greenwich",
      "type": "hourly_resampled",
      "source": "PEINP_GR_WeatherStn_Sep2024.csv",
      "path": "data/processed/greenwich/station_hourly.csv",
      "rows": 720,
      "timestamp": "2026-03-25T09:57:58.124787+00:00"
    },
    {
      "station": "greenwich",
      "type": "daily_resampled",
      "source": "PEINP_GR_WeatherStn_Sep2024.csv",
      "path": "data/processed/greenwich/station_daily.csv",
      "rows": 31,
      "timestamp": "2026-03-25T09:57:58.124793+00:00"
    },
    {
      "station": "greenwich",
      "type": "hourly_resampled",
      "source": "PEINP_GR_WeatherStn_Apr2025.csv",
      "path": "data/processed/greenwich/station_hourly.csv",
      "rows": 720,
      "timestamp": "2026-03-25T09:57:58.194514+00:00"
    },
    {
      "station": "greenwich",
      "type": "daily_resampled",
      "source": "PEINP_GR_WeatherStn_Apr2025.csv",
      "path": "data/processed/greenwich/station_daily.csv",
      "rows": 31,
      "timestamp": "2026-03-25T09:57:58.194520+00:00"
    },
    {
      "station": "greenwich",
      "type": "hourly_resampled",
      "source": "PEINP_GR_WeatherStn_Aug2025.csv",
      "path": "data/processed/greenwich/station_hourly.csv",
      "rows": 744,
      "timestamp": "2026-03-25T09:57:58.266198+00:00"
    },
    {
      "station": "greenwich",
      "type": "daily_resampled",
      "source": "PEINP_GR_WeatherStn_Aug2025.csv",
      "path": "data/processed/greenwich/station_daily.csv",
      "rows": 32,
      "timestamp": "2026-03-25T09:57:58.266204+00:00"
    },
    {
      "station": "greenwich",
      "type": "hourly_resampled",
      "source": "PEINP_GR_WeatherStn_Dec2025.csv",
      "path": "data/processed/greenwich/station_hourly.csv",
      "rows": 744,
      "timestamp": "2026-03-25T09:57:58.338118+00:00"
    },
    {
      "station": "greenwich",
      "type": "daily_resampled",
      "source": "PEINP_GR_WeatherStn_Dec2025.csv",
      "path": "data/processed/greenwich/station_daily.csv",
      "rows": 32,
      "timestamp": "2026-03-25T09:57:58.338125+00:00"
    },
    {
      "station": "greenwich",
      "type": "hourly_resampled",
      "source": "PEINP_GR_WeatherStn_Feb2025.csv",
      "path": "data/processed/greenwich/station_hourly.csv",
      "rows": 672,
      "timestamp": "2026-03-25T09:57:58.401344+00:00"
    },
    {
      "station": "greenwich",
      "type": "daily_resampled",
      "source": "PEINP_GR_WeatherStn_Feb2025.csv",
      "path": "data/processed/greenwich/station_daily.csv",
      "rows": 29,
      "timestamp": "2026-03-25T09:57:58.401350+00:00"
    },
    {
      "station": "greenwich",
      "type": "hourly_resampled",
      "source": "PEINP_GR_WeatherStn_Jan2025.csv",
      "path": "data/processed/greenwich/station_hourly.csv",
      "rows": 744,
      "timestamp": "2026-03-25T09:57:58.471954+00:00"
    },
    {
      "station": "greenwich",
      "type": "daily_resampled",
      "source": "PEINP_GR_WeatherStn_Jan2025.csv",
      "path": "data/processed/greenwich/station_daily.csv",
      "rows": 32,
      "timestamp": "2026-03-25T09:57:58.471961+00:00"
    },
    {
      "station": "greenwich",
      "type": "hourly_resampled",
      "source": "PEINP_GR_WeatherStn_Jul2025.csv",
      "path": "data/processed/greenwich/station_hourly.csv",
      "rows": 744,
      "timestamp": "2026-03-25T09:57:58.543059+00:00"
    },
    {
      "station": "greenwich",
      "type": "daily_resampled",
      "source": "PEINP_GR_WeatherStn_Jul2025.csv",
      "path": "data/processed/greenwich/station_daily.csv",
      "rows": 32,
      "timestamp": "2026-03-25T09:57:58.543066+00:00"
    },
    {
      "station": "greenwich",
      "type": "hourly_resampled",
      "source": "PEINP_GR_WeatherStn_Jun2025.csv",
      "path": "data/processed/greenwich/station_hourly.csv",
      "rows": 720,
      "timestamp": "2026-03-25T09:57:58.611715+00:00"
    },
    {
      "station": "greenwich",
      "type": "daily_resampled",
      "source": "PEINP_GR_WeatherStn_Jun2025.csv",
      "path": "data/processed/greenwich/station_daily.csv",
      "rows": 31,
      "timestamp": "2026-03-25T09:57:58.611721+00:00"
    },
    {
      "station": "greenwich",
      "type": "hourly_resampled",
      "source": "PEINP_GR_WeatherStn_Mar2025.csv",
      "path": "data/processed/greenwich/station_hourly.csv",
      "rows": 743,
      "timestamp": "2026-03-25T09:57:58.700141+00:00"
    },
    {
      "station": "greenwich",
      "type": "daily_resampled",
      "source": "PEINP_GR_WeatherStn_Mar2025.csv",
      "path": "data/processed/greenwich/station_daily.csv",
      "rows": 32,
      "timestamp": "2026-03-25T09:57:58.700149+00:00"
    },
    {
      "station": "greenwich",
      "type": "hourly_resampled",
      "source": "PEINP_GR_WeatherStn_May2025.csv",
      "path": "data/processed/greenwich/station_hourly.csv",
      "rows": 744,
      "timestamp": "2026-03-25T09:57:58.779098+00:00"
    },
    {
      "station": "greenwich",
      "type": "daily_resampled",
      "source": "PEINP_GR_WeatherStn_May2025.csv",
      "path": "data/processed/greenwich/station_daily.csv",
      "rows": 32,
      "timestamp": "2026-03-25T09:57:58.779105+00:00"
    },
    {
      "station": "greenwich",
      "type": "hourly_resampled",
      "source": "PEINP_GR_WeatherStn_Nov2025.csv",
      "path": "data/processed/greenwich/station_hourly.csv",
      "rows": 721,
      "timestamp": "2026-03-25T09:57:58.874724+00:00"
    },
    {
      "station": "greenwich",
      "type": "daily_resampled",
      "source": "PEINP_GR_WeatherStn_Nov2025.csv",
      "path": "data/processed/greenwich/station_daily.csv",
      "rows": 31,
      "timestamp": "2026-03-25T09:57:58.874730+00:00"
    },
    {
      "station": "greenwich",
      "type": "hourly_resampled",
      "source": "PEINP_GR_WeatherStn_Oct2025.csv",
      "path": "data/processed/greenwich/station_hourly.csv",
      "rows": 744,
      "timestamp": "2026-03-25T09:57:58.945447+00:00"
    },
    {
      "station": "greenwich",
      "type": "daily_resampled",
      "source": "PEINP_GR_WeatherStn_Oct2025.csv",
      "path": "data/processed/greenwich/station_daily.csv",
      "rows": 32,
      "timestamp": "2026-03-25T09:57:58.945453+00:00"
    },
    {
      "station": "greenwich",
      "type": "hourly_resampled",
      "source": "PEINP_GR_WeatherStn_Sep2025.csv",
      "path": "data/processed/greenwich/station_hourly.csv",
      "rows": 720,
      "timestamp": "2026-03-25T09:57:59.016642+00:00"
    },
    {
      "station": "greenwich",
      "type": "daily_resampled",
      "source": "PEINP_GR_WeatherStn_Sep2025.csv",
      "path": "data/processed/greenwich/station_daily.csv",
      "rows": 31,
      "timestamp": "2026-03-25T09:57:59.016649+00:00"
    },
    {
      "station": "greenwich",
      "type": "hourly_cleaned",
      "path": "data/processed/greenwich/station_hourly.csv",
      "rows": 28715,
      "timestamp": "2026-03-25T09:58:00.794221+00:00"
    },
    {
      "station": "greenwich",
      "type": "daily_cleaned",
      "path": "data/processed/greenwich/station_daily.csv",
      "rows": 1241,
      "timestamp": "2026-03-25T09:58:00.794230+00:00"
    },
    {
      "type": "imputation_report",
      "path": "data/processed/imputation_report.csv",
      "rows": 543,
      "timestamp": "2026-03-25T09:58:00.795823+00:00"
    },
    {
      "station": "stanhope",
      "type": "hourly_normalized",
      "path": "data/processed/stanhope/station_hourly.csv",
      "rows": 29208,
      "timestamp": "2026-03-25T09:58:01.386388+00:00"
    }
  ]
}
